pingdetect/__init__.py
pingdetect/detect_spatial.py
pingdetect/rf_infer_folder.py
pingdetect/rf_infer_tracker.py
pingdetect/rf_utils.py
pingdetect/version.py
pingdetect-1.0.0b7.dist-info/METADATA
pingdetect-1.0.0b7.dist-info/WHEEL
pingdetect-1.0.0b7.dist-info/top_level.txt
pingdetect-1.0.0b7.dist-info/RECORD
